rxw/__init__.py
rxw/_version.py
rxw/app.py
rxw/models.py
rxw/openweathermap.py
rx_weather-2.0.1.dist-info/LICENSE.txt
rx_weather-2.0.1.dist-info/METADATA
rx_weather-2.0.1.dist-info/WHEEL
rx_weather-2.0.1.dist-info/entry_points.txt
rx_weather-2.0.1.dist-info/top_level.txt
rx_weather-2.0.1.dist-info/RECORD
