Metadata-Version: 2.1
Name: rx-weather
Version: 2.0.1
Summary: demo app to fetch weather using requests and rxpy
Home-page: https://github.com/barnardn/rx_weather
Author: Norm Barnard
Author-email: norm@normbarnard.com
License: MIT
Keywords: rx,python,weather,demo
Platform: UNKNOWN
Classifier: Development Status :: 4 - Beta
Classifier: License :: OSI Approved :: MIT License
Classifier: Programming Language :: Python :: 3.6
Classifier: Topic :: Utilities
Requires-Python: ~=3.6
Requires-Dist: certifi
Requires-Dist: chardet
Requires-Dist: funcy
Requires-Dist: idna
Requires-Dist: pytz
Requires-Dist: requests
Requires-Dist: rx
Requires-Dist: rx-weather
Requires-Dist: tzlocal
Requires-Dist: urllib3
